stellanow_cli/__init__.py
stellanow_cli/_run.py
stellanow_cli/cli.py
stellanow_cli/code_generators/__init__.py
stellanow_cli/code_generators/common/__init__.py
stellanow_cli/code_generators/common/code_generator.py
stellanow_cli/code_generators/common/templates/footer.jinja2
stellanow_cli/code_generators/common/templates/header.jinja2
stellanow_cli/code_generators/csharp/__init__.py
stellanow_cli/code_generators/csharp/code_generator.py
stellanow_cli/code_generators/csharp/templates/message.jinja2
stellanow_cli/code_generators/csharp/templates/model.jinja2
stellanow_cli/code_generators/python/__init__.py
stellanow_cli/code_generators/python/code_generator.py
stellanow_cli/code_generators/python/templates/message.jinja2
stellanow_cli/code_generators/python/templates/model.jinja2
stellanow_cli/code_generators/typescript/__init__.py
stellanow_cli/code_generators/typescript/code_generator.py
stellanow_cli/code_generators/typescript/templates/message.jinja2
stellanow_cli/code_generators/typescript/templates/model.jinja2
stellanow_cli/commands/_init__.py
stellanow_cli/commands/code_generator/__init__.py
stellanow_cli/commands/code_generator/code_generator_service_group.py
stellanow_cli/commands/code_generator/events.py
stellanow_cli/commands/code_generator/generate.py
stellanow_cli/commands/code_generator/models.py
stellanow_cli/commands/configure/__init__.py
stellanow_cli/commands/configure/code_generator.py
stellanow_cli/commands/configure/configure_group.py
stellanow_cli/commands/data_dna_stream_tester/__init__.py
stellanow_cli/commands/data_dna_stream_tester/data_dna_stream_tester_group.py
stellanow_cli/commands/data_dna_stream_tester/send_game_state_data.py
stellanow_cli/core/__init__.py
stellanow_cli/core/context.py
stellanow_cli/core/decorators.py
stellanow_cli/core/enums.py
stellanow_cli/core/helpers.py
stellanow_cli/core/logger.py
stellanow_cli/core/profile_manager.py
stellanow_cli/core/utils/__init__.py
stellanow_cli/core/utils/logger_utils.py
stellanow_cli-0.0.16.dist-info/METADATA
stellanow_cli-0.0.16.dist-info/WHEEL
stellanow_cli-0.0.16.dist-info/entry_points.txt
stellanow_cli-0.0.16.dist-info/RECORD
