Metadata-Version: 2.3
Name: stellanow-cli
Version: 0.0.16
Summary: Command-line interface for the StellaNow SDK code generation and comparison tool.
License: MIT
Author: Stella Technologies (UK) Limited
Requires-Python: >=3.11,<4.0
Classifier: License :: OSI Approved :: MIT License
Classifier: Programming Language :: Python :: 3
Classifier: Programming Language :: Python :: 3.11
Classifier: Programming Language :: Python :: 3.12
Classifier: Programming Language :: Python :: 3.13
Requires-Dist: click (>=8.1,<9.0)
Requires-Dist: inflection (>=0.5.1,<0.6.0)
Requires-Dist: jinja2 (>=3.1.6,<3.2.0)
Requires-Dist: loguru (>=0.7,<1.0)
Requires-Dist: paho-mqtt (>=2.1.0,<2.2.0)
Requires-Dist: prettytable (>=3.8,<4.0)
Requires-Dist: stellanow-api-internals (>=0.0.5,<0.1.0)
